flybrainlab/Client.py
flybrainlab/GFXComponent.py
flybrainlab/NeurokernelComponent.py
flybrainlab/__init__.py
flybrainlab/circuit.py
flybrainlab/diagram_generator.py
flybrainlab/exceptions.py
flybrainlab/ffbolabRunGFX.py
flybrainlab/graph.py
flybrainlab/nk_component_runner.py
flybrainlab/query.py
flybrainlab/run_nk_component.py
flybrainlab/utils.py
flybrainlab/widget.py
flybrainlab/utilities/__init__.py
flybrainlab/utilities/neuroembed.py
flybrainlab/utilities/neurograph.py
flybrainlab/utilities/neurometry.py
flybrainlab/utilities/neurosynapsis.py
flybrainlab/utilities/neurowatch.py
FlyBrainLab-1.1.11.dist-info/LICENSE
FlyBrainLab-1.1.11.dist-info/METADATA
FlyBrainLab-1.1.11.dist-info/WHEEL
FlyBrainLab-1.1.11.dist-info/top_level.txt
FlyBrainLab-1.1.11.dist-info/RECORD
