Metadata-Version: 2.1
Name: FlyBrainLab
Version: 1.1.11
Summary: FlyBrainLab User-side Backend
Home-page: https://flybrainlab.fruitflybrain.org
Download-URL: 
Author: Mehmet Kerem Turkcan, Yiyin Zhou
Author-email: mkt2126@columbia.edu, yiyin.zhou@fordham.edu
License: BSD-3-Clause
Requires-Python: >=3.6
License-File: LICENSE
Requires-Dist: numpy
Requires-Dist: txaio
Requires-Dist: h5py
Requires-Dist: autobahn
Requires-Dist: twisted[tls]
Requires-Dist: autobahn-sync
Requires-Dist: pyOpenSSL
Requires-Dist: seaborn
Requires-Dist: requests
Requires-Dist: msgpack >1.0
Requires-Dist: msgpack-numpy
Requires-Dist: neuroballad
Requires-Dist: matplotlib
Requires-Dist: networkx
Requires-Dist: pandas
Requires-Dist: ipython
Requires-Dist: graphviz
Requires-Dist: jupyterlab <3.6,>=3.0
Requires-Dist: pywin32 ; platform_system == "Windows"
Requires-Dist: dataclasses ; python_version < "3.7"
Provides-Extra: full
Requires-Dist: graspy <=0.1.1 ; extra == 'full'
Requires-Dist: scikit-learn ; extra == 'full'
Requires-Dist: tensorflow ; extra == 'full'
Requires-Dist: nxt-gem ==2.0.1 ; extra == 'full'
Requires-Dist: cdlib ; extra == 'full'
Requires-Dist: umap-learn ; extra == 'full'
Requires-Dist: scipy ; extra == 'full'
Requires-Dist: pyclustering ; extra == 'full'
Provides-Extra: utilities
Requires-Dist: graspy <=0.1.1 ; extra == 'utilities'
Requires-Dist: scikit-learn ; extra == 'utilities'
Requires-Dist: tensorflow ; extra == 'utilities'
Requires-Dist: nxt-gem ==2.0.1 ; extra == 'utilities'
Requires-Dist: cdlib ; extra == 'utilities'
Requires-Dist: umap-learn ; extra == 'utilities'
Requires-Dist: scipy ; extra == 'utilities'
Requires-Dist: pyclustering ; extra == 'utilities'
